pyansiwrap/__init__.py
pyansiwrap-1.0.0.dist-info/METADATA
pyansiwrap-1.0.0.dist-info/WHEEL
pyansiwrap-1.0.0.dist-info/licenses/LICENSE.txt
pyansiwrap-1.0.0.dist-info/RECORD
