Metadata-Version: 2.4
Name: pyansiwrap
Version: 1.0.0
Summary: A simple, zero-dependency package for adding ANSI color and style to terminal text.
Author-email: Tarun Simha <tarunsimha2509@gmail.com>
License-File: LICENSE.txt
Classifier: License :: OSI Approved :: MIT License
Classifier: Operating System :: OS Independent
Classifier: Programming Language :: Python :: 3
Classifier: Topic :: Terminals
Requires-Python: >=3.7
